setup.py
gb_prob_distributions/Binomialdistribution.py
gb_prob_distributions/Gaussiandistribution.py
gb_prob_distributions/Generaldistribution.py
gb_prob_distributions/__init__.py
gb_prob_distributions.egg-info/PKG-INFO
gb_prob_distributions.egg-info/SOURCES.txt
gb_prob_distributions.egg-info/dependency_links.txt
gb_prob_distributions.egg-info/not-zip-safe
gb_prob_distributions.egg-info/top_level.txt