Metadata-Version: 1.0
Name: gb-prob-distributions
Version: 1.0
Summary: Gaussian and Binomial distributions
Home-page: UNKNOWN
Author: Ritvik Iyer
Author-email: ritvik95.iyer@gmail.com
License: UNKNOWN
Platform: UNKNOWN
